enzoic/__init__.py
enzoic/enzoic.py
enzoic/exceptions.py
enzoic/enums/__init__.py
enzoic/enums/password_types.py
enzoic/utilities/__init__.py
enzoic/utilities/hashing.py
tests/__init__.py
tests/conftest.py
tests/test_enzoic.py
tests/test_hashes.py
enzoic-1.50.dist-info/LICENSE
enzoic-1.50.dist-info/METADATA
enzoic-1.50.dist-info/WHEEL
enzoic-1.50.dist-info/top_level.txt
enzoic-1.50.dist-info/RECORD
