Metadata-Version: 2.1
Name: enzoic
Version: 1.50
Summary: Python Client for Enzoic
Home-page: https://github.com/Enzoic/enzoic-python-client
Author: Enzoic
Author-email: mike@enzoic.com
Classifier: Programming Language :: Python :: 3
Classifier: License :: OSI Approved :: MIT License
Classifier: Operating System :: OS Independent
License-File: LICENSE
Requires-Dist: requests
Requires-Dist: pytest
Requires-Dist: passlib
Requires-Dist: bcrypt
Requires-Dist: argon2-cffi ==23.1.0
